oai_repo/__init__.py
oai_repo/error.py
oai_repo/exceptions.py
oai_repo/getrecord.py
oai_repo/helpers.py
oai_repo/identify.py
oai_repo/interface.py
oai_repo/interfacedata.py
oai_repo/listidentifiers.py
oai_repo/listmetadataformats.py
oai_repo/listrecords.py
oai_repo/listsets.py
oai_repo/repository.py
oai_repo/request.py
oai_repo/response.py
oai_repo/resumption.py
oai_repo/transform.py
oai_repo/validators.py
oai_repo-0.5.1.dist-info/LICENSE
oai_repo-0.5.1.dist-info/METADATA
oai_repo-0.5.1.dist-info/WHEEL
oai_repo-0.5.1.dist-info/top_level.txt
oai_repo-0.5.1.dist-info/RECORD
