Metadata-Version: 2.1
Name: oai_repo
Version: 0.5.1
Summary: OAI-PMH Repository Server
Home-page: https://github.com/MSU-Libraries/oai_repo
Author: Nate Collins
Author-email: npcollins@gmail.com
License: Apache License 2.0
Project-URL: Documentation, https://msu-libraries.github.io/oai_repo/
Classifier: Intended Audience :: Developers
Classifier: Development Status :: 4 - Beta
Classifier: License :: OSI Approved :: Apache Software License
Classifier: Operating System :: OS Independent
Classifier: Programming Language :: Python
Classifier: Programming Language :: Python :: 3
Classifier: Programming Language :: Python :: 3.10
Requires-Python: >=3.10
License-File: LICENSE
Requires-Dist: Cerberus>=1.3
Requires-Dist: jsonpath-ng>=1.6
Requires-Dist: lxml>=4.9
Requires-Dist: requests>=2.31
Requires-Dist: validators>=0.22
